LICENSE
README.md
setup.py
NlpToolkit_SpellChecker.egg-info/PKG-INFO
NlpToolkit_SpellChecker.egg-info/SOURCES.txt
NlpToolkit_SpellChecker.egg-info/dependency_links.txt
NlpToolkit_SpellChecker.egg-info/requires.txt
NlpToolkit_SpellChecker.egg-info/top_level.txt
SpellChecker/Candidate.py
SpellChecker/ContextBasedSpellChecker.py
SpellChecker/NGramSpellChecker.py
SpellChecker/Operator.py
SpellChecker/SimpleSpellChecker.py
SpellChecker/SpellChecker.py
SpellChecker/SpellCheckerParameter.py
SpellChecker/Trie.py
SpellChecker/TrieBasedSpellChecker.py
SpellChecker/TrieCandidate.py
SpellChecker/TrieNode.py
SpellChecker/__init__.py