Metadata-Version: 2.1
Name: NlpToolkit-SpellChecker
Version: 1.0.25
Summary: Turkish Spell Checker Library
Home-page: https://github.com/StarlangSoftware/TurkishSpellChecker-Py
Author: olcaytaner
Author-email: olcay.yildiz@ozyegin.edu.tr
License: UNKNOWN
Platform: UNKNOWN
